<?xml version="1.0" encoding="UTF-8" standalone="yes"?>

<item>
<title>El planeta de los simios 1968 </title>        
<urlsolve>http://streamcloud.eu/5g5afviphc5n/El.Planeta.De.Los.Simios.1968.DVDRip__www.oranline.com_.avi.html</urlsolve>
<thumbnail>http://www.fotos.org/galeria/data/576/1968-El-planeta-de-los-simios-Franklin-J-Schaffner-esp-2.JPG</thumbnail>
<fanart>http://www.mubis.es/media/users/1414/13602/el-planeta-de-los-simios-1968-franklin-j-schaffner-original.jpg</fanart>
</item>

<item>
<title>Regreso al planeta delos simios 1970 </title>        
<urlsolve>http://streamcloud.eu/7goutjo4eq40/Regreso.Al.Planeta.De.Los.Simios.1970.DVDRip__www.oranline.com_.avi.html</urlsolve>
<thumbnail>https://teenagethunder.files.wordpress.com/2012/03/cartel.jpg</thumbnail>
<fanart>http://www.mubis.es/media/users/1414/13599/el-planeta-de-los-simios-1968-franklin-j-schaffner-original.jpg</fanart>
</item>

<item>
<title>Huida del planeta de los simios 1971 </title>        
<urlsolve>http://streamcloud.eu/ucqfml1orhk6/Huida.Del.Planeta.De.Los.Simios.1971.DVDRip__www.oranline.com_.avi.html</urlsolve>
<thumbnail>http://i718.photobucket.com/albums/ww184/sykrayo/iacutendice_zps7ie9uhfq.jpg</thumbnail>
<fanart>http://i.imgur.com/VD02Dvw.jpg</fanart>
</item>

<item>
<title>La Conquista del planeta de los simios 1972 </title>        
<urlsolve>http://romeo.exabytetv.info/pelicula/YAAIC-1011001011000110110111111010101-ExabyteTV-holis/YmF0YWxsYS1wb3ItZWwtcGxhbmV0YS1kZS1sb3Mtc2ltaW9zLw==/visita-exabytetv.mp4</urlsolve>
<thumbnail>https://upload.wikimedia.org/wikipedia/en/1/18/Conquest_of_the_planet_of_the_apes.jpg</thumbnail>
<fanart>https://image.tmdb.org/t/p/original/d1eNYl1qVRFVR0xWFSefb2C6QWa.jpg</fanart>
</item>

<item>
<title>La rebelión de los simios 1972 </title>        
<urlsolve>http://streamcloud.eu/5jtjm03oq2s4/La.Rebelion.De.Los.Simios.1972.DVDRip__www.oranline.com_.avi.html</urlsolve>
<thumbnail>http://pics.filmaffinity.com/La_rebeli_n_de_los_simios-282926792-large.jpg</thumbnail>
<fanart>http://www.dmtinc.cl/imagenes/Ah82.jpg</fanart>
</item>

<item>
<title>Batalla por el planeta de los simios 1973 </title>        
<urlsolve>http://streamcloud.eu/0g3cuq3tcrv3/Batalla.por.el..Planeta.De.los.Simios.1973.DVDRip__www.oranline.com_.avi.html</urlsolve>
<thumbnail>http://www.planetasimios.com/images/comic1.jpg</thumbnail>
<fanart>http://www.pocosmegashd.net/wp-content/uploads/2016/10/La-Conquista-Del-Planeta-De-Los-Simios-1973-BRRip-Dual-Latino-1080p-3.jpg</fanart>
</item>

<item>
<title>El planeta de los simios 2001 </title>        
<urlsolve>http://romeo.exabytetv.info/pelicula/YAAIC-1011001011000110110111111010101-ExabyteTV-holis/ZWwtcGxhbmV0YS1kZS1sb3Mtc2ltaW9zLS8=/visita-exabytetv.mp4</urlsolve>
<thumbnail>https://lavozenoffdotnet.files.wordpress.com/2014/07/planeta-simios-1.jpg</thumbnail>
<fanart>https://image.tmdb.org/t/p/original/r87F9i3JyJbCym8zNtdciEnexOS.jpg</fanart>
</item>

<item>
<title>El amanecer del Planeta de los Simios 2014 </title>        
<urlsolve>http://streamcloud.eu/uv6sawg4k0a4/SIMIOS.AMANECE._2014_.HDRip.XviD.AC3.5.1.Castellano.avi.html</urlsolve>
<thumbnail>http://www.pixelon.es/wp-content/uploads/2013/12/EL-AMANECER-DEL-PLANETA-DE-LOS-SIMIOS-pixelon.jpg</thumbnail>
<fanart>https://i.ytimg.com/vi/Oie455BvRe0/maxresdefault.jpg</fanart>
</item>